imagecat/LeagueSpartan-SemiBold.ttf
imagecat/__init__.py
imagecat/data.py
imagecat/expression.py
imagecat/io.py
imagecat/notebook.py
imagecat/optional.py
imagecat/require.py
imagecat/units.py
imagecat/color/__init__.py
imagecat/color/basic.py
imagecat/color/brewer.py
imagecat/operator/__init__.py
imagecat/operator/blur.py
imagecat/operator/color.py
imagecat/operator/cryptomatte.py
imagecat/operator/noise.py
imagecat/operator/render.py
imagecat/operator/transform.py
imagecat/operator/util.py
imagecat-0.7.0.dist-info/LICENSE
imagecat-0.7.0.dist-info/WHEEL
imagecat-0.7.0.dist-info/METADATA
imagecat-0.7.0.dist-info/RECORD
